stdlib/__init__.py
stdlib/hexdump.py
stdlib/loan.py
stdlib/matrices.py
stdlib/stdexceptions.py
stdlib/abstracts/__init__.py
stdlib/abstracts/abstractcollection.py
stdlib/abstracts/abstractmap.py
stdlib/abstracts/abstractset.py
stdlib/abstracts/collection.py
stdlib/abstracts/comparable.py
stdlib/abstracts/comparator.py
stdlib/abstracts/iterable.py
stdlib/abstracts/iterator.py
stdlib/abstracts/map.py
stdlib/abstracts/navigablemap.py
stdlib/abstracts/sortedmap.py
stdlib/abstracts/transparency.py
stdlib/linear_ds/__init__.py
stdlib/linear_ds/bag.py
stdlib/linear_ds/bst.py
stdlib/linear_ds/heap.py
stdlib/linear_ds/indexminpq.py
stdlib/linear_ds/maxpq.py
stdlib/linear_ds/minpq.py
stdlib/linear_ds/queue.py
stdlib/linear_ds/redblackbst.py
stdlib/linear_ds/set.py
stdlib/linear_ds/stack.py
stdlib/linear_ds/symbolgraph.py
stdlib/linear_ds/symboltable.py
stdlib/linear_ds/treemap.py
stdlib/non_linear_ds/__init__.py
stdlib/non_linear_ds/depthfirstdirectedpaths.py
stdlib/non_linear_ds/depthfirstorder.py
stdlib/non_linear_ds/depthfirstpaths.py
stdlib/non_linear_ds/depthfirstsearch.py
stdlib/non_linear_ds/digraph.py
stdlib/non_linear_ds/digraphgenerator.py
stdlib/non_linear_ds/dijkstra.py
stdlib/non_linear_ds/directedDFS.py
stdlib/non_linear_ds/directededge.py
stdlib/non_linear_ds/edge.py
stdlib/non_linear_ds/edgeweighteddigraph.py
stdlib/non_linear_ds/edgeweightedgraph.py
stdlib/non_linear_ds/graph.py
stdlib/sorting/__init__.py
stdlib/sorting/insertionx.py
stdlib/sorting/merge.py
stdlib/sorting/mergex.py
stdlib/sorting/quick3way.py
stdlib/sorting/quickx.py
stdlib/stdlib/__init__.py
stdlib/stdlib/binarysearch.py
stdlib/stdlib/collections.py
stdlib/stdlib/complex.py
stdlib/stdlib/singleton.py
stdlib/stdlib/stats.py
stdlib/stdlib/stdin.py
stdlib/utils/__init__.py
stdlib/utils/arrayIO.py
stdlib/utils/fft.py
stdlib/utils/inn.py
stdlib/utils/particle.py
stdlib/utils/randomwordgenerator.py
stdlib/utils/recthv.py
stdlib/utils/scanner.py
complete_stdlib-0.0.1.dist-info/LICENSE
complete_stdlib-0.0.1.dist-info/METADATA
complete_stdlib-0.0.1.dist-info/WHEEL
complete_stdlib-0.0.1.dist-info/top_level.txt
complete_stdlib-0.0.1.dist-info/RECORD
