Metadata-Version: 2.1
Name: complete-stdlib
Version: 0.0.1
Summary: A standard library for python
Home-page: UNKNOWN
Author: Anonymous
Author-email: 
License: UNKNOWN
Platform: UNKNOWN
Classifier: Programming Language :: Python :: 3
Classifier: License :: OSI Approved :: MIT License
Classifier: Operating System :: OS Independent
